test/__init__.py
test/test_youtube.py
thumbframes_dl/__init__.py
thumbframes_dl/utils.py
thumbframes_dl/version.py
thumbframes_dl/extractors/__init__.py
thumbframes_dl/extractors/youtube.py
thumbframes_dl/extractors/base/__init__.py
thumbframes_dl/extractors/base/format.py
thumbframes_dl/extractors/base/frames.py
thumbframes_dl/extractors/base/image.py
thumbframes_dl-0.15.0.dist-info/LICENSE
thumbframes_dl-0.15.0.dist-info/METADATA
thumbframes_dl-0.15.0.dist-info/WHEEL
thumbframes_dl-0.15.0.dist-info/top_level.txt
thumbframes_dl-0.15.0.dist-info/RECORD
