Metadata-Version: 2.1
Name: thumbframes-dl
Version: 0.15.0
Summary: Download thumbnail frames from a video's progress bar
Home-page: https://github.com/MarcAbonce/thumbframes_dl
Author: Marc Abonce Seguin
License: Unlicense
Keywords: videos,youtube,download,frames,thumbnails,storyboards
Classifier: Topic :: Multimedia :: Video
Classifier: Topic :: Software Development :: Libraries
Classifier: License :: Public Domain
Classifier: Development Status :: 4 - Beta
Classifier: Intended Audience :: Developers
Classifier: Programming Language :: Python
Classifier: Programming Language :: Python :: 3
License-File: LICENSE
Requires-Dist: youtube-dl==2021.12.17
